fxc_logger/__init__.py
fxc_logger/context.py
fxc_logger/functions.py
fxc_logger-1.0.2.dist-info/METADATA
fxc_logger-1.0.2.dist-info/WHEEL
fxc_logger-1.0.2.dist-info/top_level.txt
fxc_logger-1.0.2.dist-info/RECORD
