Metadata-Version: 2.4
Name: fxc_logger
Version: 1.0.2
Summary: Python library for logging with colors and http status code.
Home-page: https://github.com/frexco-digital/fxc-logger.git
Keywords: logs logging logger
Classifier: Intended Audience :: Developers
Classifier: Programming Language :: Python
Classifier: Programming Language :: Python :: 3.10
Requires-Dist: requests
Dynamic: classifier
Dynamic: description
Dynamic: description-content-type
Dynamic: home-page
Dynamic: keywords
Dynamic: requires-dist
Dynamic: summary
